pyriichi/__init__.py
pyriichi/game_state.py
pyriichi/hand.py
pyriichi/rules.py
pyriichi/rules_config.py
pyriichi/scoring.py
pyriichi/tiles.py
pyriichi/utils.py
pyriichi/yaku.py
pyriichi-0.1.0.dist-info/licenses/LICENSE
pyriichi-0.1.0.dist-info/METADATA
pyriichi-0.1.0.dist-info/WHEEL
pyriichi-0.1.0.dist-info/top_level.txt
pyriichi-0.1.0.dist-info/RECORD
