Metadata-Version: 2.4
Name: pyriichi
Version: 0.1.0
Summary: A complete implementation of Japanese Mahjong (Riichi Mahjong) rules engine
Author: PyRiichi Contributors
License: MIT
Project-URL: Homepage, https://github.com/d4n1elchen/pyriichi
Project-URL: Documentation, https://github.com/d4n1elchen/pyriichi#readme
Project-URL: Bug Reports, https://github.com/d4n1elchen/pyriichi/issues
Project-URL: Source, https://github.com/d4n1elchen/pyriichi
Keywords: mahjong,riichi,japanese,game,engine
Classifier: Development Status :: 3 - Alpha
Classifier: Intended Audience :: Developers
Classifier: Topic :: Games/Entertainment :: Board Games
Classifier: License :: OSI Approved :: MIT License
Classifier: Programming Language :: Python :: 3
Classifier: Programming Language :: Python :: 3.8
Classifier: Programming Language :: Python :: 3.9
Classifier: Programming Language :: Python :: 3.10
Classifier: Programming Language :: Python :: 3.11
Classifier: Programming Language :: Python :: 3.12
Requires-Python: >=3.8
License-File: LICENSE
Provides-Extra: dev
Requires-Dist: pytest>=7.0.0; extra == "dev"
Requires-Dist: pytest-cov>=4.0.0; extra == "dev"
Requires-Dist: black>=23.0.0; extra == "dev"
Requires-Dist: flake8>=6.0.0; extra == "dev"
Requires-Dist: mypy>=1.0.0; extra == "dev"
Provides-Extra: test
Requires-Dist: pytest>=7.0.0; extra == "test"
Requires-Dist: pytest-cov>=4.0.0; extra == "test"
Dynamic: license-file
